{
    "name": "HTML Component",
    "selector": "component.html",
    "editor": "editor.html",
    "tools": [{
            "name": "special",
            "tool": "tinymce"
        },
        {
            "name": "inline",
            "tool": "inline"
        },
        {
            "name": "erase",
            "tool": "erase"
        },
        {
            "name": "fullscreen",
            "tool": "fullscreen"
        }
    ],
    "specialEditor": "editor.special.tinymce",
    "version": 1.0,
    "content": "<div data-component=\"image\">\n    <img src=\"/src/assets/images/clean-office.jpg\" class=\"img-responsive img-component\" />\n    <span class=\"image-sub-text\">Small caption for the above image</span>\n</div>",
    "scripts": [
        "/src/scripts/script1.js",
        "/src/scripts/script2.js"
    ]
}